setup.py
access_manager/__init__.py
access_manager/http.py
access_manager/models.py
access_manager/requirements.py
access_manager/views.py
access_manager/tests/__init__.py
access_manager/tests/factories.py
access_manager/tests/requirements.py
access_manager/tests/views.py
django_access_manager.egg-info/PKG-INFO
django_access_manager.egg-info/SOURCES.txt
django_access_manager.egg-info/dependency_links.txt
django_access_manager.egg-info/requires.txt
django_access_manager.egg-info/top_level.txt