Metadata-Version: 1.1
Name: django-access-manager
Version: 0.0.2
Summary: An abstract access manager for Django.
Home-page: http://github.com/FundedByMe/django-access-manager
Author: Anton Agestam
Author-email: msn@antonagestam.se
License: UNKNOWN
Platform: UNKNOWN
Classifier: Framework :: Django
Classifier: Intended Audience :: Developers
Classifier: Intended Audience :: System Administrators
Classifier: Operating System :: OS Independent
Classifier: Topic :: Software Development
